v_ml_program/__init__.py
v_ml_program/iris_classifier.py
v_ml_program/text_classifier.py
v_ml_program-0.2.dist-info/METADATA
v_ml_program-0.2.dist-info/WHEEL
v_ml_program-0.2.dist-info/top_level.txt
v_ml_program-0.2.dist-info/RECORD
